README.md
setup.cfg
setup.py
xgboost_tuner/__init__.py
xgboost_tuner/tuner.py
xgboost_tuner.egg-info/PKG-INFO
xgboost_tuner.egg-info/SOURCES.txt
xgboost_tuner.egg-info/dependency_links.txt
xgboost_tuner.egg-info/requires.txt
xgboost_tuner.egg-info/top_level.txt