Metadata-Version: 1.1
Name: xgboost-tuner
Version: 0.1.1
Summary: XGBoost Automatic Parameter Tuning Library
Home-page: https://github.com/cwerner87/xgboost_tuner
Author: cwerner87
Author-email: cwerner87@users.noreply.github.com
License: GPL v3
Platform: UNKNOWN
Classifier: Development Status :: 5 - Production/Stable
Classifier: Operating System :: Microsoft :: Windows
Classifier: Operating System :: POSIX
Classifier: Operating System :: Unix
Classifier: Operating System :: MacOS
Classifier: Programming Language :: Python :: 3
Classifier: Programming Language :: Python :: 3.3
Classifier: Programming Language :: Python :: 3.4
Classifier: Programming Language :: Python :: 3.5
Classifier: Topic :: Scientific/Engineering
Classifier: Topic :: Scientific/Engineering :: Artificial Intelligence
Classifier: Topic :: Scientific/Engineering :: Information Analysis
